Metadata-Version: 2.1
Name: bookhack-ikoblyk
Version: 2.0.0
Summary: Book downloading tool
Home-page: https://github.com/ikoblyk/IMAGES_TO_DVU_BOOK.git
Author: Ivan Koblyk
Author-email: ivankob.16@gmail.com
License: UNKNOWN
Platform: UNKNOWN
Classifier: Programming Language :: Python :: 3
Classifier: License :: OSI Approved :: MIT License
Classifier: Operating System :: POSIX :: Linux
Requires-Python: >=3.6
